ollamatk/__init__.py
ollamatk/__main__.py
ollamatk/about.py
ollamatk/app.py
ollamatk/chat.py
ollamatk/event_thread.py
ollamatk/http.py
ollamatk/logging.py
ollamatk/messages.py
ollamatk/py.typed
ollamatk/scrollable_frame.py
ollamatk/settings.py
ollamatk/wrap_label.py
ollamatk/icons/assistant.png
ollamatk/icons/user.png
ollama_tk-1.0.5.dist-info/LICENSE
ollama_tk-1.0.5.dist-info/METADATA
ollama_tk-1.0.5.dist-info/WHEEL
ollama_tk-1.0.5.dist-info/entry_points.txt
ollama_tk-1.0.5.dist-info/top_level.txt
ollama_tk-1.0.5.dist-info/RECORD
