Metadata-Version: 2.1
Name: ollama-tk
Version: 1.0.5
Summary: A tkinter GUI for interacting with any Ollama API.
Author: thegamecracks
License: MIT
Project-URL: Homepage, https://github.com/thegamecracks/ollama-tk
Project-URL: Issue Tracker, https://github.com/thegamecracks/ollama-tk/issues
Classifier: Development Status :: 5 - Production/Stable
Classifier: Framework :: AsyncIO
Classifier: Intended Audience :: End Users/Desktop
Classifier: License :: OSI Approved
Classifier: License :: OSI Approved :: MIT License
Classifier: Programming Language :: Python
Classifier: Programming Language :: Python :: 3
Classifier: Programming Language :: Python :: 3.11
Classifier: Programming Language :: Python :: 3.12
Classifier: Topic :: Scientific/Engineering
Classifier: Topic :: Scientific/Engineering :: Artificial Intelligence
Classifier: Typing :: Typed
Requires-Python: >=3.11
License-File: LICENSE
Requires-Dist: httpx >=0.27.2
